CHANGELOG.txt
LICENCE.txt
MANIFEST.in
README.txt
setup.py
VoiceAsistant.egg-info/PKG-INFO
VoiceAsistant.egg-info/SOURCES.txt
VoiceAsistant.egg-info/dependency_links.txt
VoiceAsistant.egg-info/requires.txt
VoiceAsistant.egg-info/top_level.txt
ilkay/__init__.py