Metadata-Version: 1.1
Name: VoiceAsistant
Version: 2.0.0
Summary: Speak Voice Asistants
Home-page: https://github.com/ilkay-alti/TalkinVoiceAssistant
Author: ilkay altınışık
Author-email: ilkayalti@hotmail.com
License: MIT
Keywords: ArisaVoiceAsistant
Platform: UNKNOWN
Classifier: Development Status :: 5 - Production/Stable
Classifier: Intended Audience :: Education
Classifier: Operating System :: Microsoft :: Windows :: Windows 10
Classifier: License :: OSI Approved :: MIT License
Classifier: Programming Language :: Python :: 3
